webcitizen_boss333/__init__.py
webcitizen_boss333/webcitizen.py
webcitizen-0.1.0.dist-info/LICENSE
webcitizen-0.1.0.dist-info/METADATA
webcitizen-0.1.0.dist-info/WHEEL
webcitizen-0.1.0.dist-info/top_level.txt
webcitizen-0.1.0.dist-info/RECORD
