Metadata-Version: 2.1
Name: webcitizen
Version: 0.1.0
Summary: SEO audits for websites
Project-URL: homepage, https://github.com/pypa/sampleproject
License-File: LICENSE
